bench/__init__.py
bench/__init__.pyr
bench/app.py
bench/bench.py
bench/cli.py
bench/exceptions.py
bench/commands/__init__.py
bench/commands/config.py
bench/commands/git.py
bench/commands/install.py
bench/commands/make.py
bench/commands/setup.py
bench/commands/update.py
bench/commands/utils.py
bench/config/__init__.py
bench/config/common_site_config.py
bench/config/lets_encrypt.py
bench/config/nginx.py
bench/config/procfile.py
bench/config/production_setup.py
bench/config/redis.py
bench/config/site_config.py
bench/config/supervisor.py
bench/config/systemd.py
bench/config/templates/502.html
bench/config/templates/Procfile
bench/config/templates/bench_manager_nginx.conf
bench/config/templates/flexlar_sudoers
bench/config/templates/letsencrypt.cfg
bench/config/templates/nginx.conf
bench/config/templates/nginx_default.conf
bench/config/templates/redis_cache.conf
bench/config/templates/redis_queue.conf
bench/config/templates/supervisor.conf
bench/config/templates/systemd/flexlar-bench-flexlar-default-worker.service
bench/config/templates/systemd/flexlar-bench-flexlar-long-worker.service
bench/config/templates/systemd/flexlar-bench-flexlar-schedule.service
bench/config/templates/systemd/flexlar-bench-flexlar-short-worker.service
bench/config/templates/systemd/flexlar-bench-flexlar-web.service
bench/config/templates/systemd/flexlar-bench-node-socketio.service
bench/config/templates/systemd/flexlar-bench-redis-cache.service
bench/config/templates/systemd/flexlar-bench-redis-queue.service
bench/config/templates/systemd/flexlar-bench-redis.target
bench/config/templates/systemd/flexlar-bench-web.target
bench/config/templates/systemd/flexlar-bench-workers.target
bench/config/templates/systemd/flexlar-bench.target
bench/patches/__init__.py
bench/patches/patches.txt
bench/playbooks/README.md
bench/playbooks/create_user.yml
bench/playbooks/macosx.yml
bench/playbooks/site.yml
bench/playbooks/vm_build.yml
bench/playbooks/roles/bash_screen_wall/files/screen_wall.sh
flexlar_bench-1.0.0.dist-info/METADATA
flexlar_bench-1.0.0.dist-info/WHEEL
flexlar_bench-1.0.0.dist-info/entry_points.txt
flexlar_bench-1.0.0.dist-info/RECORD
