Metadata-Version: 2.4
Name: flexlar-bench
Version: 1.0.0
Summary: CLI to manage Multi-tenant deployments for Flexlar apps
Project-URL: Changelog, https://github.com/flexlar/bench/releases
Project-URL: Documentation, https://flexlarframework.com/docs/user/en/bench
Project-URL: Homepage, https://flexlar.io/bench
Project-URL: Source, https://github.com/flexlar/bench
Author-email: Flexlar Technologies Pvt Ltd <developers@flexlar.io>
License-Expression: GPL-3.0-only
Classifier: Development Status :: 5 - Production/Stable
Classifier: Environment :: Console
Classifier: License :: OSI Approved :: GNU General Public License v3 (GPLv3)
Classifier: Natural Language :: English
Classifier: Operating System :: MacOS
Classifier: Operating System :: OS Independent
Classifier: Topic :: Software Development :: Build Tools
Classifier: Topic :: Software Development :: User Interfaces
Classifier: Topic :: System :: Installation/Setup
Requires-Python: >=3.10
Requires-Dist: click~=8.2.0
Requires-Dist: gitpython~=3.1.30
Requires-Dist: honcho
Requires-Dist: jinja2~=3.1.3
Requires-Dist: python-crontab~=2.6.0
Requires-Dist: requests~=2.32.5
Requires-Dist: semantic-version~=2.10.0
Requires-Dist: setuptools>=71.0.0
Requires-Dist: tomli; python_version < '3.11'
Requires-Dist: uv~=0.9.0
